textremo_toolbox/MatlabFuncHelper.py
textremo_toolbox/__init__.py
textremo_toolbox-1.0.11.dist-info/METADATA
textremo_toolbox-1.0.11.dist-info/WHEEL
textremo_toolbox-1.0.11.dist-info/top_level.txt
textremo_toolbox-1.0.11.dist-info/RECORD
