Metadata-Version: 2.2
Name: textremo_toolbox
Version: 1.0.11
Requires-Dist: numpy>=1.20.1
Dynamic: description
Dynamic: description-content-type
Dynamic: requires-dist
